glmdenoise/__init__.py
glmdenoise/console.py
glmdenoise/cross_validate.py
glmdenoise/defaults.py
glmdenoise/fit_runs.py
glmdenoise/pyGlmdenoise.py
glmdenoise/r2_nom_denom.py
glmdenoise/report.py
glmdenoise/select_noise_regressors.py
glmdenoise/whiten_data.py
glmdenoise/io/__init__.py
glmdenoise/io/bids.py
glmdenoise/io/directory.py
glmdenoise/io/files.py
glmdenoise/io/input.py
glmdenoise/io/output.py
glmdenoise/io/public.py
glmdenoise/utils/R2_nom_denom.py
glmdenoise/utils/__init__.py
glmdenoise/utils/choose.py
glmdenoise/utils/get_poly_matrix.py
glmdenoise/utils/gethrf.py
glmdenoise/utils/isrowvector.py
glmdenoise/utils/make_design_matrix.py
glmdenoise/utils/make_image_stack.py
glmdenoise/utils/make_poly_matrix.py
glmdenoise/utils/normalisemax.py
glmdenoise/utils/optimiseHRF.py
tests/__init__.py
tests/bids.py
tests/directory.py
tests/files.py
tests/main.py
tests/output.py
tests/select_noise_regressors.py
glmdenoise-0.0.5.dist-info/METADATA
glmdenoise-0.0.5.dist-info/WHEEL
glmdenoise-0.0.5.dist-info/entry_points.txt
glmdenoise-0.0.5.dist-info/top_level.txt
glmdenoise-0.0.5.dist-info/RECORD
