Metadata-Version: 2.1
Name: glmdenoise
Version: 0.0.5
Summary: Python GLMdenoise
Home-page: https://github.com/Charestlab/pyGLMdenoise
Maintainer: Jasper van den Bosch
Maintainer-email: vandejjf@bham.ac.uk
License: UNKNOWN
Keywords: neuroscience
Platform: UNKNOWN
Classifier: Programming Language :: Python
Classifier: Development Status :: 1 - Planning
Classifier: License :: OSI Approved :: GNU Lesser General Public License v3 (LGPLv3)
Classifier: Topic :: Scientific/Engineering
Classifier: Intended Audience :: Science/Research
Requires-Dist: numpy
Requires-Dist: scipy
Requires-Dist: sklearn
Requires-Dist: matplotlib
Requires-Dist: twine
Requires-Dist: sphinx
Requires-Dist: seaborn
Requires-Dist: pybids (==0.8.0)
Requires-Dist: duecredit
Requires-Dist: ww
Requires-Dist: numba
Requires-Dist: tqdm
Requires-Dist: joblib
Requires-Dist: datalad
Requires-Dist: imageio
